{
    "packages": {
        "wordpress\/back-to-top": {
            "1.0": {
                "name": "wordpress\/back-to-top",
                "version": "1.0",
                "version_normalized": "1.0.0.0",
                "dist": {
                    "type": "zip",
                    "url": "http:\/\/downloads.wordpress.org\/plugin\/back-to-top.1.0.zip",
                    "reference": null,
                    "shasum": null
                },
                "require": {
                    "wordpress\/installer": "0.1.*"
                },
                "type": "wordpress-plugin",
                "description": "<p>\u5728\u9875\u9762\u7684\u5de6\u4fa7\u6216\u8005\u53f3\u4fa7\u521b\u5efa\u4e00\u4e2a&#8220;\u8fd4\u56de\u9876\u90e8&#8221;\u7684\u6309\u94ae\uff0c\u4f7f\u7528&#8220;\u8fd4\u56de\u9876\u90e8&#8221;\u6309\u94ae\uff0c\u53ef\u4ee5\u65b9\u4fbf\u5feb\u6377\u5e73\u6ed1\u7684\u8fd4\u56de\u5230blog\u7684\u9876\u90e8\u3002<\/p>\n\n<p>This WordPress plugin adds an \"Back To Top\" button to easily scroll long pages back to the top.<\/p>",
                "uid": "36737"
            },
            "1.1": {
                "name": "wordpress\/back-to-top",
                "version": "1.1",
                "version_normalized": "1.1.0.0",
                "dist": {
                    "type": "zip",
                    "url": "http:\/\/downloads.wordpress.org\/plugin\/back-to-top.1.1.zip",
                    "reference": null,
                    "shasum": null
                },
                "require": {
                    "wordpress\/installer": "0.1.*"
                },
                "type": "wordpress-plugin",
                "description": "<p>\u5728\u9875\u9762\u7684\u5de6\u4fa7\u6216\u8005\u53f3\u4fa7\u521b\u5efa\u4e00\u4e2a&#8220;\u8fd4\u56de\u9876\u90e8&#8221;\u7684\u6309\u94ae\uff0c\u4f7f\u7528&#8220;\u8fd4\u56de\u9876\u90e8&#8221;\u6309\u94ae\uff0c\u53ef\u4ee5\u65b9\u4fbf\u5feb\u6377\u5e73\u6ed1\u7684\u8fd4\u56de\u5230blog\u7684\u9876\u90e8\u3002<\/p>\n\n<p>This WordPress plugin adds an \"Back To Top\" button to easily scroll long pages back to the top.<\/p>",
                "uid": "36736"
            },
            "1.2": {
                "name": "wordpress\/back-to-top",
                "version": "1.2",
                "version_normalized": "1.2.0.0",
                "dist": {
                    "type": "zip",
                    "url": "http:\/\/downloads.wordpress.org\/plugin\/back-to-top.1.2.zip",
                    "reference": null,
                    "shasum": null
                },
                "require": {
                    "wordpress\/installer": "0.1.*"
                },
                "type": "wordpress-plugin",
                "description": "<p>\u5728\u9875\u9762\u7684\u5de6\u4fa7\u6216\u8005\u53f3\u4fa7\u521b\u5efa\u4e00\u4e2a&#8220;\u8fd4\u56de\u9876\u90e8&#8221;\u7684\u6309\u94ae\uff0c\u4f7f\u7528&#8220;\u8fd4\u56de\u9876\u90e8&#8221;\u6309\u94ae\uff0c\u53ef\u4ee5\u65b9\u4fbf\u5feb\u6377\u5e73\u6ed1\u7684\u8fd4\u56de\u5230blog\u7684\u9876\u90e8\u3002<\/p>\n\n<p>This WordPress plugin adds an \"Back To Top\" button to easily scroll long pages back to the top.<\/p>",
                "uid": "36735"
            },
            "1.3": {
                "name": "wordpress\/back-to-top",
                "version": "1.3",
                "version_normalized": "1.3.0.0",
                "dist": {
                    "type": "zip",
                    "url": "http:\/\/downloads.wordpress.org\/plugin\/back-to-top.1.3.zip",
                    "reference": null,
                    "shasum": null
                },
                "require": {
                    "wordpress\/installer": "0.1.*"
                },
                "type": "wordpress-plugin",
                "description": "<p>\u5728\u9875\u9762\u7684\u5de6\u4fa7\u6216\u8005\u53f3\u4fa7\u521b\u5efa\u4e00\u4e2a&#8220;\u8fd4\u56de\u9876\u90e8&#8221;\u7684\u6309\u94ae\uff0c\u4f7f\u7528&#8220;\u8fd4\u56de\u9876\u90e8&#8221;\u6309\u94ae\uff0c\u53ef\u4ee5\u65b9\u4fbf\u5feb\u6377\u5e73\u6ed1\u7684\u8fd4\u56de\u5230blog\u7684\u9876\u90e8\u3002<\/p>\n\n<p>This WordPress plugin adds an \"Back To Top\" button to easily scroll long pages back to the top.<\/p>",
                "uid": "36734"
            },
            "1.4": {
                "name": "wordpress\/back-to-top",
                "version": "1.4",
                "version_normalized": "1.4.0.0",
                "dist": {
                    "type": "zip",
                    "url": "http:\/\/downloads.wordpress.org\/plugin\/back-to-top.1.4.zip",
                    "reference": null,
                    "shasum": null
                },
                "require": {
                    "wordpress\/installer": "0.1.*"
                },
                "type": "wordpress-plugin",
                "description": "<p>\u5728\u9875\u9762\u7684\u5de6\u4fa7\u6216\u8005\u53f3\u4fa7\u521b\u5efa\u4e00\u4e2a&#8220;\u8fd4\u56de\u9876\u90e8&#8221;\u7684\u6309\u94ae\uff0c\u4f7f\u7528&#8220;\u8fd4\u56de\u9876\u90e8&#8221;\u6309\u94ae\uff0c\u53ef\u4ee5\u65b9\u4fbf\u5feb\u6377\u5e73\u6ed1\u7684\u8fd4\u56de\u5230blog\u7684\u9876\u90e8\u3002<\/p>\n\n<p>This WordPress plugin adds an \"Back To Top\" button to easily scroll long pages back to the top.<\/p>",
                "uid": "36733"
            },
            "1.5": {
                "name": "wordpress\/back-to-top",
                "version": "1.5",
                "version_normalized": "1.5.0.0",
                "dist": {
                    "type": "zip",
                    "url": "http:\/\/downloads.wordpress.org\/plugin\/back-to-top.1.5.zip",
                    "reference": null,
                    "shasum": null
                },
                "require": {
                    "wordpress\/installer": "0.1.*"
                },
                "type": "wordpress-plugin",
                "description": "<p>\u5728\u9875\u9762\u7684\u5de6\u4fa7\u6216\u8005\u53f3\u4fa7\u521b\u5efa\u4e00\u4e2a&#8220;\u8fd4\u56de\u9876\u90e8&#8221;\u7684\u6309\u94ae\uff0c\u4f7f\u7528&#8220;\u8fd4\u56de\u9876\u90e8&#8221;\u6309\u94ae\uff0c\u53ef\u4ee5\u65b9\u4fbf\u5feb\u6377\u5e73\u6ed1\u7684\u8fd4\u56de\u5230blog\u7684\u9876\u90e8\u3002<\/p>\n\n<p>This WordPress plugin adds an \"Back To Top\" button to easily scroll long pages back to the top.<\/p>",
                "uid": "36732"
            }
        }
    }
}