{
    "packages": {
        "wordpress\/church-pack": {
            "1.1": {
                "name": "wordpress\/church-pack",
                "version": "1.1",
                "version_normalized": "1.1.0.0",
                "dist": {
                    "type": "zip",
                    "url": "http:\/\/downloads.wordpress.org\/plugin\/church-pack.1.1.zip",
                    "reference": null,
                    "shasum": null
                },
                "require": {
                    "wordpress\/installer": "0.1.*"
                },
                "type": "wordpress-plugin",
                "description": "<p>Developed to meet the common needs of churches using WordPress: nicely display listings of staff, create listings of ministries or groups, create widgets without knowing HTML, add photo galleries with ease, and (PRO version only) easily manage events (one time and recurring), .<\/p>\n\n<h4>People<\/h4>\n\n<p>This can be used to add a listing of staff, teachers, deacons, elders, or even all members. People can be put into categories and then can be added to the frontend of your site with a simple shortcode to display all people or just a specific category.<\/p>\n\n<h4>Groups<\/h4>\n\n<p>Groups are designed to add a listing of ministries, small groups, classes, etc. Groups can be put into categories and added to the frontend of your site like People.<\/p>\n\n<h4>Photo Albums<\/h4>\n\n<p>Easily add albums to your church website. Photos are added using WordPress' core features &#38; displayed nicely on your site.<\/p>\n\n<h4>Content Shortcodes<\/h4>\n\n<p>Several easy to use <a href=\"http:\/\/demo.wpforchurch.co",
                "uid": "22978"
            },
            "1.2.3": {
                "name": "wordpress\/church-pack",
                "version": "1.2.3",
                "version_normalized": "1.2.3.0",
                "dist": {
                    "type": "zip",
                    "url": "http:\/\/downloads.wordpress.org\/plugin\/church-pack.1.2.3.zip",
                    "reference": null,
                    "shasum": null
                },
                "require": {
                    "wordpress\/installer": "0.1.*"
                },
                "type": "wordpress-plugin",
                "description": "<p>Developed to meet the common needs of churches using WordPress: nicely display listings of staff, create listings of ministries or groups, create widgets without knowing HTML, add photo galleries with ease, and (PRO version only) easily manage events (one time and recurring), .<\/p>\n\n<h4>People<\/h4>\n\n<p>This can be used to add a listing of staff, teachers, deacons, elders, or even all members. People can be put into categories and then can be added to the frontend of your site with a simple shortcode to display all people or just a specific category.<\/p>\n\n<h4>Groups<\/h4>\n\n<p>Groups are designed to add a listing of ministries, small groups, classes, etc. Groups can be put into categories and added to the frontend of your site like People.<\/p>\n\n<h4>Photo Albums<\/h4>\n\n<p>Easily add albums to your church website. Photos are added using WordPress' core features &#38; displayed nicely on your site.<\/p>\n\n<h4>Content Shortcodes<\/h4>\n\n<p>Several easy to use <a href=\"http:\/\/demo.wpforchurch.co",
                "uid": "125411"
            }
        }
    }
}