{
    "packages": {
        "wordpress\/embedly": {
            "1.1": {
                "name": "wordpress\/embedly",
                "version": "1.1",
                "version_normalized": "1.1.0.0",
                "dist": {
                    "type": "zip",
                    "url": "http:\/\/downloads.wordpress.org\/plugin\/embedly.1.1.zip",
                    "reference": null,
                    "shasum": null
                },
                "require": {
                    "wordpress\/installer": "0.1.*"
                },
                "type": "wordpress-plugin",
                "description": "<p>The <a href=\"http:\/\/embed.ly\">Embedly<\/a> plugin allows bloggers to embed videos, images, PDF, and article previews from\n\"any\" source with just the URL. It uses the <a href=\"http:\/\/embed.ly\/docs\">Embedly API<\/a> to\nget the embed code and display it in a post.<\/p>\n\n<p>Write your post as normal and click the Embedly Icon in your Rich Editor\nto add \"any\" URL to your post.<\/p>\n\n<p>OR<\/p>\n\n<p>Embed 200+ sources by putting the URL to the content you want to embed on\na single line like so:<\/p>\n\n<pre><code>This Embedly lets me embed everything great on the web!\n\n<a href=\"http:\/\/twitpic.com\/1owy89\" rel=\"nofollow\">http:\/\/twitpic.com\/1owy89<\/a>\n\n<a href=\"http:\/\/i.imgur.com\/ywzpg.jpg\" rel=\"nofollow\">http:\/\/i.imgur.com\/ywzpg.jpg<\/a>\n\n<a href=\"http:\/\/www.amazon.com\/gp\/product\/B002BRZ9G0\/ref=s9_pop_gw_ir01\" rel=\"nofollow\">http:\/\/www.amazon.com\/gp\/product\/B002BRZ9G0\/ref=s9_pop_gw_ir01<\/a>\n\n<a href=\"http:\/\/twitter.com\/jack\/status\/20\" rel=\"nofollow\">http:\/\/twitter.com\/jack\/status\/20<\/a>\n\n<a href=\"htt",
                "uid": "68330"
            },
            "1.2": {
                "name": "wordpress\/embedly",
                "version": "1.2",
                "version_normalized": "1.2.0.0",
                "dist": {
                    "type": "zip",
                    "url": "http:\/\/downloads.wordpress.org\/plugin\/embedly.1.2.zip",
                    "reference": null,
                    "shasum": null
                },
                "require": {
                    "wordpress\/installer": "0.1.*"
                },
                "type": "wordpress-plugin",
                "description": "<p>The <a href=\"http:\/\/embed.ly\">Embedly<\/a> plugin allows bloggers to embed videos, images, PDF, and article previews from\n\"any\" source with just the URL. It uses the <a href=\"http:\/\/embed.ly\/docs\">Embedly API<\/a> to\nget the embed code and display it in a post.<\/p>\n\n<p>Write your post as normal and click the Embedly Icon in your Rich Editor\nto add \"any\" URL to your post.<\/p>\n\n<p>OR<\/p>\n\n<p>Embed 200+ sources by putting the URL to the content you want to embed on\na single line like so:<\/p>\n\n<pre><code>This Embedly lets me embed everything great on the web!\n\n<a href=\"http:\/\/twitpic.com\/1owy89\" rel=\"nofollow\">http:\/\/twitpic.com\/1owy89<\/a>\n\n<a href=\"http:\/\/i.imgur.com\/ywzpg.jpg\" rel=\"nofollow\">http:\/\/i.imgur.com\/ywzpg.jpg<\/a>\n\n<a href=\"http:\/\/www.amazon.com\/gp\/product\/B002BRZ9G0\/ref=s9_pop_gw_ir01\" rel=\"nofollow\">http:\/\/www.amazon.com\/gp\/product\/B002BRZ9G0\/ref=s9_pop_gw_ir01<\/a>\n\n<a href=\"http:\/\/twitter.com\/jack\/status\/20\" rel=\"nofollow\">http:\/\/twitter.com\/jack\/status\/20<\/a>\n\n<a href=\"htt",
                "uid": "68329"
            },
            "1.3": {
                "name": "wordpress\/embedly",
                "version": "1.3",
                "version_normalized": "1.3.0.0",
                "dist": {
                    "type": "zip",
                    "url": "http:\/\/downloads.wordpress.org\/plugin\/embedly.1.3.zip",
                    "reference": null,
                    "shasum": null
                },
                "require": {
                    "wordpress\/installer": "0.1.*"
                },
                "type": "wordpress-plugin",
                "description": "<p>The <a href=\"http:\/\/embed.ly\">Embedly<\/a> plugin allows bloggers to embed videos, images, PDF, and article previews from\n\"any\" source with just the URL. It uses the <a href=\"http:\/\/embed.ly\/docs\">Embedly API<\/a> to\nget the embed code and display it in a post.<\/p>\n\n<p>Write your post as normal and click the Embedly Icon in your Rich Editor\nto add \"any\" URL to your post.<\/p>\n\n<p>OR<\/p>\n\n<p>Embed 200+ sources by putting the URL to the content you want to embed on\na single line like so:<\/p>\n\n<pre><code>This Embedly lets me embed everything great on the web!\n\n<a href=\"http:\/\/twitpic.com\/1owy89\" rel=\"nofollow\">http:\/\/twitpic.com\/1owy89<\/a>\n\n<a href=\"http:\/\/i.imgur.com\/ywzpg.jpg\" rel=\"nofollow\">http:\/\/i.imgur.com\/ywzpg.jpg<\/a>\n\n<a href=\"http:\/\/www.amazon.com\/gp\/product\/B002BRZ9G0\/ref=s9_pop_gw_ir01\" rel=\"nofollow\">http:\/\/www.amazon.com\/gp\/product\/B002BRZ9G0\/ref=s9_pop_gw_ir01<\/a>\n\n<a href=\"http:\/\/twitter.com\/jack\/status\/20\" rel=\"nofollow\">http:\/\/twitter.com\/jack\/status\/20<\/a>\n\n<a href=\"htt",
                "uid": "68328"
            },
            "1.4": {
                "name": "wordpress\/embedly",
                "version": "1.4",
                "version_normalized": "1.4.0.0",
                "dist": {
                    "type": "zip",
                    "url": "http:\/\/downloads.wordpress.org\/plugin\/embedly.1.4.zip",
                    "reference": null,
                    "shasum": null
                },
                "require": {
                    "wordpress\/installer": "0.1.*"
                },
                "type": "wordpress-plugin",
                "description": "<p>The <a href=\"http:\/\/embed.ly\">Embedly<\/a> plugin allows bloggers to embed videos, images, PDF, and article previews from\n\"any\" source with just the URL. It uses the <a href=\"http:\/\/embed.ly\/docs\">Embedly API<\/a> to\nget the embed code and display it in a post.<\/p>\n\n<p>Write your post as normal and click the Embedly Icon in your Rich Editor\nto add \"any\" URL to your post.<\/p>\n\n<p>OR<\/p>\n\n<p>Embed 200+ sources by putting the URL to the content you want to embed on\na single line like so:<\/p>\n\n<pre><code>This Embedly lets me embed everything great on the web!\n\n<a href=\"http:\/\/twitpic.com\/1owy89\" rel=\"nofollow\">http:\/\/twitpic.com\/1owy89<\/a>\n\n<a href=\"http:\/\/i.imgur.com\/ywzpg.jpg\" rel=\"nofollow\">http:\/\/i.imgur.com\/ywzpg.jpg<\/a>\n\n<a href=\"http:\/\/www.amazon.com\/gp\/product\/B002BRZ9G0\/ref=s9_pop_gw_ir01\" rel=\"nofollow\">http:\/\/www.amazon.com\/gp\/product\/B002BRZ9G0\/ref=s9_pop_gw_ir01<\/a>\n\n<a href=\"http:\/\/twitter.com\/jack\/status\/20\" rel=\"nofollow\">http:\/\/twitter.com\/jack\/status\/20<\/a>\n\n<a href=\"htt",
                "uid": "68327"
            },
            "2.0": {
                "name": "wordpress\/embedly",
                "version": "2.0",
                "version_normalized": "2.0.0.0",
                "dist": {
                    "type": "zip",
                    "url": "http:\/\/downloads.wordpress.org\/plugin\/embedly.2.0.zip",
                    "reference": null,
                    "shasum": null
                },
                "require": {
                    "wordpress\/installer": "0.1.*"
                },
                "type": "wordpress-plugin",
                "description": "<p>The <a href=\"http:\/\/embed.ly\">Embedly<\/a> plugin allows bloggers to embed videos, images, PDF, and article previews from\n\"any\" source with just the URL. It uses the <a href=\"http:\/\/embed.ly\/docs\">Embedly API<\/a> to\nget the embed code and display it in a post.<\/p>\n\n<p>Write your post as normal and click the Embedly Icon in your Rich Editor\nto add \"any\" URL to your post.<\/p>\n\n<p>OR<\/p>\n\n<p>Embed 200+ sources by putting the URL to the content you want to embed on\na single line like so:<\/p>\n\n<pre><code>This Embedly lets me embed everything great on the web!\n\n<a href=\"http:\/\/twitpic.com\/1owy89\" rel=\"nofollow\">http:\/\/twitpic.com\/1owy89<\/a>\n\n<a href=\"http:\/\/i.imgur.com\/ywzpg.jpg\" rel=\"nofollow\">http:\/\/i.imgur.com\/ywzpg.jpg<\/a>\n\n<a href=\"http:\/\/www.amazon.com\/gp\/product\/B002BRZ9G0\/ref=s9_pop_gw_ir01\" rel=\"nofollow\">http:\/\/www.amazon.com\/gp\/product\/B002BRZ9G0\/ref=s9_pop_gw_ir01<\/a>\n\n<a href=\"http:\/\/twitter.com\/jack\/status\/20\" rel=\"nofollow\">http:\/\/twitter.com\/jack\/status\/20<\/a>\n\n<a href=\"htt",
                "uid": "68326"
            },
            "2.0.1": {
                "name": "wordpress\/embedly",
                "version": "2.0.1",
                "version_normalized": "2.0.1.0",
                "dist": {
                    "type": "zip",
                    "url": "http:\/\/downloads.wordpress.org\/plugin\/embedly.2.0.1.zip",
                    "reference": null,
                    "shasum": null
                },
                "require": {
                    "wordpress\/installer": "0.1.*"
                },
                "type": "wordpress-plugin",
                "description": "<p>The <a href=\"http:\/\/embed.ly\">Embedly<\/a> plugin allows bloggers to embed videos, images, PDF, and article previews from\n\"any\" source with just the URL. It uses the <a href=\"http:\/\/embed.ly\/docs\">Embedly API<\/a> to\nget the embed code and display it in a post.<\/p>\n\n<p>Write your post as normal and click the Embedly Icon in your Rich Editor\nto add \"any\" URL to your post.<\/p>\n\n<p>OR<\/p>\n\n<p>Embed 200+ sources by putting the URL to the content you want to embed on\na single line like so:<\/p>\n\n<pre><code>This Embedly lets me embed everything great on the web!\n\n<a href=\"http:\/\/twitpic.com\/1owy89\" rel=\"nofollow\">http:\/\/twitpic.com\/1owy89<\/a>\n\n<a href=\"http:\/\/i.imgur.com\/ywzpg.jpg\" rel=\"nofollow\">http:\/\/i.imgur.com\/ywzpg.jpg<\/a>\n\n<a href=\"http:\/\/www.amazon.com\/gp\/product\/B002BRZ9G0\/ref=s9_pop_gw_ir01\" rel=\"nofollow\">http:\/\/www.amazon.com\/gp\/product\/B002BRZ9G0\/ref=s9_pop_gw_ir01<\/a>\n\n<a href=\"http:\/\/twitter.com\/jack\/status\/20\" rel=\"nofollow\">http:\/\/twitter.com\/jack\/status\/20<\/a>\n\n<a href=\"htt",
                "uid": "68325"
            },
            "2.0.2": {
                "name": "wordpress\/embedly",
                "version": "2.0.2",
                "version_normalized": "2.0.2.0",
                "dist": {
                    "type": "zip",
                    "url": "http:\/\/downloads.wordpress.org\/plugin\/embedly.2.0.2.zip",
                    "reference": null,
                    "shasum": null
                },
                "require": {
                    "wordpress\/installer": "0.1.*"
                },
                "type": "wordpress-plugin",
                "description": "<p>The <a href=\"http:\/\/embed.ly\">Embedly<\/a> plugin allows bloggers to embed videos, images, PDF, and article previews from\n\"any\" source with just the URL. It uses the <a href=\"http:\/\/embed.ly\/docs\">Embedly API<\/a> to\nget the embed code and display it in a post.<\/p>\n\n<p>Write your post as normal and click the Embedly Icon in your Rich Editor\nto add \"any\" URL to your post.<\/p>\n\n<p>OR<\/p>\n\n<p>Embed 200+ sources by putting the URL to the content you want to embed on\na single line like so:<\/p>\n\n<pre><code>This Embedly lets me embed everything great on the web!\n\n<a href=\"http:\/\/twitpic.com\/1owy89\" rel=\"nofollow\">http:\/\/twitpic.com\/1owy89<\/a>\n\n<a href=\"http:\/\/i.imgur.com\/ywzpg.jpg\" rel=\"nofollow\">http:\/\/i.imgur.com\/ywzpg.jpg<\/a>\n\n<a href=\"http:\/\/www.amazon.com\/gp\/product\/B002BRZ9G0\/ref=s9_pop_gw_ir01\" rel=\"nofollow\">http:\/\/www.amazon.com\/gp\/product\/B002BRZ9G0\/ref=s9_pop_gw_ir01<\/a>\n\n<a href=\"http:\/\/twitter.com\/jack\/status\/20\" rel=\"nofollow\">http:\/\/twitter.com\/jack\/status\/20<\/a>\n\n<a href=\"htt",
                "uid": "68324"
            },
            "2.0.3": {
                "name": "wordpress\/embedly",
                "version": "2.0.3",
                "version_normalized": "2.0.3.0",
                "dist": {
                    "type": "zip",
                    "url": "http:\/\/downloads.wordpress.org\/plugin\/embedly.2.0.3.zip",
                    "reference": null,
                    "shasum": null
                },
                "require": {
                    "wordpress\/installer": "0.1.*"
                },
                "type": "wordpress-plugin",
                "description": "<p>The <a href=\"http:\/\/embed.ly\">Embedly<\/a> plugin allows bloggers to embed videos, images, PDF, and article previews from\n\"any\" source with just the URL. It uses the <a href=\"http:\/\/embed.ly\/docs\">Embedly API<\/a> to\nget the embed code and display it in a post.<\/p>\n\n<p>Write your post as normal and click the Embedly Icon in your Rich Editor\nto add \"any\" URL to your post.<\/p>\n\n<p>OR<\/p>\n\n<p>Embed 200+ sources by putting the URL to the content you want to embed on\na single line like so:<\/p>\n\n<pre><code>This Embedly lets me embed everything great on the web!\n\n<a href=\"http:\/\/twitpic.com\/1owy89\" rel=\"nofollow\">http:\/\/twitpic.com\/1owy89<\/a>\n\n<a href=\"http:\/\/i.imgur.com\/ywzpg.jpg\" rel=\"nofollow\">http:\/\/i.imgur.com\/ywzpg.jpg<\/a>\n\n<a href=\"http:\/\/www.amazon.com\/gp\/product\/B002BRZ9G0\/ref=s9_pop_gw_ir01\" rel=\"nofollow\">http:\/\/www.amazon.com\/gp\/product\/B002BRZ9G0\/ref=s9_pop_gw_ir01<\/a>\n\n<a href=\"http:\/\/twitter.com\/jack\/status\/20\" rel=\"nofollow\">http:\/\/twitter.com\/jack\/status\/20<\/a>\n\n<a href=\"htt",
                "uid": "68323"
            },
            "2.0.4": {
                "name": "wordpress\/embedly",
                "version": "2.0.4",
                "version_normalized": "2.0.4.0",
                "dist": {
                    "type": "zip",
                    "url": "http:\/\/downloads.wordpress.org\/plugin\/embedly.2.0.4.zip",
                    "reference": null,
                    "shasum": null
                },
                "require": {
                    "wordpress\/installer": "0.1.*"
                },
                "type": "wordpress-plugin",
                "description": "<p>The <a href=\"http:\/\/embed.ly\">Embedly<\/a> plugin allows bloggers to embed videos, images, PDF, and article previews from\n\"any\" source with just the URL. It uses the <a href=\"http:\/\/embed.ly\/docs\">Embedly API<\/a> to\nget the embed code and display it in a post.<\/p>\n\n<p>Write your post as normal and click the Embedly Icon in your Rich Editor\nto add \"any\" URL to your post.<\/p>\n\n<p>OR<\/p>\n\n<p>Embed 200+ sources by putting the URL to the content you want to embed on\na single line like so:<\/p>\n\n<pre><code>This Embedly lets me embed everything great on the web!\n\n<a href=\"http:\/\/twitpic.com\/1owy89\" rel=\"nofollow\">http:\/\/twitpic.com\/1owy89<\/a>\n\n<a href=\"http:\/\/i.imgur.com\/ywzpg.jpg\" rel=\"nofollow\">http:\/\/i.imgur.com\/ywzpg.jpg<\/a>\n\n<a href=\"http:\/\/www.amazon.com\/gp\/product\/B002BRZ9G0\/ref=s9_pop_gw_ir01\" rel=\"nofollow\">http:\/\/www.amazon.com\/gp\/product\/B002BRZ9G0\/ref=s9_pop_gw_ir01<\/a>\n\n<a href=\"http:\/\/twitter.com\/jack\/status\/20\" rel=\"nofollow\">http:\/\/twitter.com\/jack\/status\/20<\/a>\n\n<a href=\"htt",
                "uid": "68322"
            },
            "2.0.5": {
                "name": "wordpress\/embedly",
                "version": "2.0.5",
                "version_normalized": "2.0.5.0",
                "dist": {
                    "type": "zip",
                    "url": "http:\/\/downloads.wordpress.org\/plugin\/embedly.2.0.5.zip",
                    "reference": null,
                    "shasum": null
                },
                "require": {
                    "wordpress\/installer": "0.1.*"
                },
                "type": "wordpress-plugin",
                "description": "<p>The <a href=\"http:\/\/embed.ly\">Embedly<\/a> plugin allows bloggers to embed videos, images, PDF, and article previews from\n\"any\" source with just the URL. It uses the <a href=\"http:\/\/embed.ly\/docs\">Embedly API<\/a> to\nget the embed code and display it in a post.<\/p>\n\n<p>Write your post as normal and click the Embedly Icon in your Rich Editor\nto add \"any\" URL to your post.<\/p>\n\n<p>OR<\/p>\n\n<p>Embed 200+ sources by putting the URL to the content you want to embed on\na single line like so:<\/p>\n\n<pre><code>This Embedly lets me embed everything great on the web!\n\n<a href=\"http:\/\/twitpic.com\/1owy89\" rel=\"nofollow\">http:\/\/twitpic.com\/1owy89<\/a>\n\n<a href=\"http:\/\/i.imgur.com\/ywzpg.jpg\" rel=\"nofollow\">http:\/\/i.imgur.com\/ywzpg.jpg<\/a>\n\n<a href=\"http:\/\/www.amazon.com\/gp\/product\/B002BRZ9G0\/ref=s9_pop_gw_ir01\" rel=\"nofollow\">http:\/\/www.amazon.com\/gp\/product\/B002BRZ9G0\/ref=s9_pop_gw_ir01<\/a>\n\n<a href=\"http:\/\/twitter.com\/jack\/status\/20\" rel=\"nofollow\">http:\/\/twitter.com\/jack\/status\/20<\/a>\n\n<a href=\"htt",
                "uid": "68321"
            },
            "2.0.6": {
                "name": "wordpress\/embedly",
                "version": "2.0.6",
                "version_normalized": "2.0.6.0",
                "dist": {
                    "type": "zip",
                    "url": "http:\/\/downloads.wordpress.org\/plugin\/embedly.2.0.6.zip",
                    "reference": null,
                    "shasum": null
                },
                "require": {
                    "wordpress\/installer": "0.1.*"
                },
                "type": "wordpress-plugin",
                "description": "<p>The <a href=\"http:\/\/embed.ly\">Embedly<\/a> plugin allows bloggers to embed videos, images, PDF, and article previews from\n\"any\" source with just the URL. It uses the <a href=\"http:\/\/embed.ly\/docs\">Embedly API<\/a> to\nget the embed code and display it in a post.<\/p>\n\n<p>Write your post as normal and click the Embedly Icon in your Rich Editor\nto add \"any\" URL to your post.<\/p>\n\n<p>OR<\/p>\n\n<p>Embed 200+ sources by putting the URL to the content you want to embed on\na single line like so:<\/p>\n\n<pre><code>This Embedly lets me embed everything great on the web!\n\n<a href=\"http:\/\/twitpic.com\/1owy89\" rel=\"nofollow\">http:\/\/twitpic.com\/1owy89<\/a>\n\n<a href=\"http:\/\/i.imgur.com\/ywzpg.jpg\" rel=\"nofollow\">http:\/\/i.imgur.com\/ywzpg.jpg<\/a>\n\n<a href=\"http:\/\/www.amazon.com\/gp\/product\/B002BRZ9G0\/ref=s9_pop_gw_ir01\" rel=\"nofollow\">http:\/\/www.amazon.com\/gp\/product\/B002BRZ9G0\/ref=s9_pop_gw_ir01<\/a>\n\n<a href=\"http:\/\/twitter.com\/jack\/status\/20\" rel=\"nofollow\">http:\/\/twitter.com\/jack\/status\/20<\/a>\n\n<a href=\"htt",
                "uid": "68320"
            },
            "2.0.7": {
                "name": "wordpress\/embedly",
                "version": "2.0.7",
                "version_normalized": "2.0.7.0",
                "dist": {
                    "type": "zip",
                    "url": "http:\/\/downloads.wordpress.org\/plugin\/embedly.2.0.7.zip",
                    "reference": null,
                    "shasum": null
                },
                "require": {
                    "wordpress\/installer": "0.1.*"
                },
                "type": "wordpress-plugin",
                "description": "<p>The <a href=\"http:\/\/embed.ly\">Embedly<\/a> plugin allows bloggers to embed videos, images, PDF, and article previews from\n\"any\" source with just the URL. It uses the <a href=\"http:\/\/embed.ly\/docs\">Embedly API<\/a> to\nget the embed code and display it in a post.<\/p>\n\n<p>Write your post as normal and click the Embedly Icon in your Rich Editor\nto add \"any\" URL to your post.<\/p>\n\n<p>OR<\/p>\n\n<p>Embed 200+ sources by putting the URL to the content you want to embed on\na single line like so:<\/p>\n\n<pre><code>This Embedly lets me embed everything great on the web!\n\n<a href=\"http:\/\/twitpic.com\/1owy89\" rel=\"nofollow\">http:\/\/twitpic.com\/1owy89<\/a>\n\n<a href=\"http:\/\/i.imgur.com\/ywzpg.jpg\" rel=\"nofollow\">http:\/\/i.imgur.com\/ywzpg.jpg<\/a>\n\n<a href=\"http:\/\/www.amazon.com\/gp\/product\/B002BRZ9G0\/ref=s9_pop_gw_ir01\" rel=\"nofollow\">http:\/\/www.amazon.com\/gp\/product\/B002BRZ9G0\/ref=s9_pop_gw_ir01<\/a>\n\n<a href=\"http:\/\/twitter.com\/jack\/status\/20\" rel=\"nofollow\">http:\/\/twitter.com\/jack\/status\/20<\/a>\n\n<a href=\"htt",
                "uid": "68319"
            },
            "2.0.8": {
                "name": "wordpress\/embedly",
                "version": "2.0.8",
                "version_normalized": "2.0.8.0",
                "dist": {
                    "type": "zip",
                    "url": "http:\/\/downloads.wordpress.org\/plugin\/embedly.2.0.8.zip",
                    "reference": null,
                    "shasum": null
                },
                "require": {
                    "wordpress\/installer": "0.1.*"
                },
                "type": "wordpress-plugin",
                "description": "<p>The <a href=\"http:\/\/embed.ly\">Embedly<\/a> plugin allows bloggers to embed videos, images, PDF, and article previews from\n\"any\" source with just the URL. It uses the <a href=\"http:\/\/embed.ly\/docs\">Embedly API<\/a> to\nget the embed code and display it in a post.<\/p>\n\n<p>Write your post as normal and click the Embedly Icon in your Rich Editor\nto add \"any\" URL to your post.<\/p>\n\n<p>OR<\/p>\n\n<p>Embed 200+ sources by putting the URL to the content you want to embed on\na single line like so:<\/p>\n\n<pre><code>This Embedly lets me embed everything great on the web!\n\n<a href=\"http:\/\/twitpic.com\/1owy89\" rel=\"nofollow\">http:\/\/twitpic.com\/1owy89<\/a>\n\n<a href=\"http:\/\/i.imgur.com\/ywzpg.jpg\" rel=\"nofollow\">http:\/\/i.imgur.com\/ywzpg.jpg<\/a>\n\n<a href=\"http:\/\/www.amazon.com\/gp\/product\/B002BRZ9G0\/ref=s9_pop_gw_ir01\" rel=\"nofollow\">http:\/\/www.amazon.com\/gp\/product\/B002BRZ9G0\/ref=s9_pop_gw_ir01<\/a>\n\n<a href=\"http:\/\/twitter.com\/jack\/status\/20\" rel=\"nofollow\">http:\/\/twitter.com\/jack\/status\/20<\/a>\n\n<a href=\"htt",
                "uid": "68318"
            },
            "2.0.9": {
                "name": "wordpress\/embedly",
                "version": "2.0.9",
                "version_normalized": "2.0.9.0",
                "dist": {
                    "type": "zip",
                    "url": "http:\/\/downloads.wordpress.org\/plugin\/embedly.2.0.9.zip",
                    "reference": null,
                    "shasum": null
                },
                "require": {
                    "wordpress\/installer": "0.1.*"
                },
                "type": "wordpress-plugin",
                "description": "<p>The <a href=\"http:\/\/embed.ly\">Embedly<\/a> plugin allows bloggers to embed videos, images, PDF, and article previews from\n\"any\" source with just the URL. It uses the <a href=\"http:\/\/embed.ly\/docs\">Embedly API<\/a> to\nget the embed code and display it in a post.<\/p>\n\n<p>Write your post as normal and click the Embedly Icon in your Rich Editor\nto add \"any\" URL to your post.<\/p>\n\n<p>OR<\/p>\n\n<p>Embed 200+ sources by putting the URL to the content you want to embed on\na single line like so:<\/p>\n\n<pre><code>This Embedly lets me embed everything great on the web!\n\n<a href=\"http:\/\/twitpic.com\/1owy89\" rel=\"nofollow\">http:\/\/twitpic.com\/1owy89<\/a>\n\n<a href=\"http:\/\/i.imgur.com\/ywzpg.jpg\" rel=\"nofollow\">http:\/\/i.imgur.com\/ywzpg.jpg<\/a>\n\n<a href=\"http:\/\/www.amazon.com\/gp\/product\/B002BRZ9G0\/ref=s9_pop_gw_ir01\" rel=\"nofollow\">http:\/\/www.amazon.com\/gp\/product\/B002BRZ9G0\/ref=s9_pop_gw_ir01<\/a>\n\n<a href=\"http:\/\/twitter.com\/jack\/status\/20\" rel=\"nofollow\">http:\/\/twitter.com\/jack\/status\/20<\/a>\n\n<a href=\"htt",
                "uid": "68317"
            },
            "2.1": {
                "name": "wordpress\/embedly",
                "version": "2.1",
                "version_normalized": "2.1.0.0",
                "dist": {
                    "type": "zip",
                    "url": "http:\/\/downloads.wordpress.org\/plugin\/embedly.2.1.zip",
                    "reference": null,
                    "shasum": null
                },
                "require": {
                    "wordpress\/installer": "0.1.*"
                },
                "type": "wordpress-plugin",
                "description": "<p>The <a href=\"http:\/\/embed.ly\">Embedly<\/a> plugin allows bloggers to embed videos, images, PDF, and article previews from\n\"any\" source with just the URL. It uses the <a href=\"http:\/\/embed.ly\/docs\">Embedly API<\/a> to\nget the embed code and display it in a post.<\/p>\n\n<p>Write your post as normal and click the Embedly Icon in your Rich Editor\nto add \"any\" URL to your post.<\/p>\n\n<p>OR<\/p>\n\n<p>Embed 200+ sources by putting the URL to the content you want to embed on\na single line like so:<\/p>\n\n<pre><code>This Embedly lets me embed everything great on the web!\n\n<a href=\"http:\/\/twitpic.com\/1owy89\" rel=\"nofollow\">http:\/\/twitpic.com\/1owy89<\/a>\n\n<a href=\"http:\/\/i.imgur.com\/ywzpg.jpg\" rel=\"nofollow\">http:\/\/i.imgur.com\/ywzpg.jpg<\/a>\n\n<a href=\"http:\/\/www.amazon.com\/gp\/product\/B002BRZ9G0\/ref=s9_pop_gw_ir01\" rel=\"nofollow\">http:\/\/www.amazon.com\/gp\/product\/B002BRZ9G0\/ref=s9_pop_gw_ir01<\/a>\n\n<a href=\"http:\/\/twitter.com\/jack\/status\/20\" rel=\"nofollow\">http:\/\/twitter.com\/jack\/status\/20<\/a>\n\n<a href=\"htt",
                "uid": "68316"
            },
            "2.1.1": {
                "name": "wordpress\/embedly",
                "version": "2.1.1",
                "version_normalized": "2.1.1.0",
                "dist": {
                    "type": "zip",
                    "url": "http:\/\/downloads.wordpress.org\/plugin\/embedly.2.1.1.zip",
                    "reference": null,
                    "shasum": null
                },
                "require": {
                    "wordpress\/installer": "0.1.*"
                },
                "type": "wordpress-plugin",
                "description": "<p>The <a href=\"http:\/\/embed.ly\">Embedly<\/a> plugin allows bloggers to embed videos, images, PDF, and article previews from\n\"any\" source with just the URL. It uses the <a href=\"http:\/\/embed.ly\/docs\">Embedly API<\/a> to\nget the embed code and display it in a post.<\/p>\n\n<p>Write your post as normal and click the Embedly Icon in your Rich Editor\nto add \"any\" URL to your post.<\/p>\n\n<p>OR<\/p>\n\n<p>Embed 200+ sources by putting the URL to the content you want to embed on\na single line like so:<\/p>\n\n<pre><code>This Embedly lets me embed everything great on the web!\n\n<a href=\"http:\/\/twitpic.com\/1owy89\" rel=\"nofollow\">http:\/\/twitpic.com\/1owy89<\/a>\n\n<a href=\"http:\/\/i.imgur.com\/ywzpg.jpg\" rel=\"nofollow\">http:\/\/i.imgur.com\/ywzpg.jpg<\/a>\n\n<a href=\"http:\/\/www.amazon.com\/gp\/product\/B002BRZ9G0\/ref=s9_pop_gw_ir01\" rel=\"nofollow\">http:\/\/www.amazon.com\/gp\/product\/B002BRZ9G0\/ref=s9_pop_gw_ir01<\/a>\n\n<a href=\"http:\/\/twitter.com\/jack\/status\/20\" rel=\"nofollow\">http:\/\/twitter.com\/jack\/status\/20<\/a>\n\n<a href=\"htt",
                "uid": "68315"
            },
            "2.1.2": {
                "name": "wordpress\/embedly",
                "version": "2.1.2",
                "version_normalized": "2.1.2.0",
                "dist": {
                    "type": "zip",
                    "url": "http:\/\/downloads.wordpress.org\/plugin\/embedly.2.1.2.zip",
                    "reference": null,
                    "shasum": null
                },
                "require": {
                    "wordpress\/installer": "0.1.*"
                },
                "type": "wordpress-plugin",
                "description": "<p>The <a href=\"http:\/\/embed.ly\">Embedly<\/a> plugin allows bloggers to embed videos, images, PDF, and article previews from\n\"any\" source with just the URL. It uses the <a href=\"http:\/\/embed.ly\/docs\">Embedly API<\/a> to\nget the embed code and display it in a post.<\/p>\n\n<p>Write your post as normal and click the Embedly Icon in your Rich Editor\nto add \"any\" URL to your post.<\/p>\n\n<p>OR<\/p>\n\n<p>Embed 200+ sources by putting the URL to the content you want to embed on\na single line like so:<\/p>\n\n<pre><code>This Embedly lets me embed everything great on the web!\n\n<a href=\"http:\/\/twitpic.com\/1owy89\" rel=\"nofollow\">http:\/\/twitpic.com\/1owy89<\/a>\n\n<a href=\"http:\/\/i.imgur.com\/ywzpg.jpg\" rel=\"nofollow\">http:\/\/i.imgur.com\/ywzpg.jpg<\/a>\n\n<a href=\"http:\/\/www.amazon.com\/gp\/product\/B002BRZ9G0\/ref=s9_pop_gw_ir01\" rel=\"nofollow\">http:\/\/www.amazon.com\/gp\/product\/B002BRZ9G0\/ref=s9_pop_gw_ir01<\/a>\n\n<a href=\"http:\/\/twitter.com\/jack\/status\/20\" rel=\"nofollow\">http:\/\/twitter.com\/jack\/status\/20<\/a>\n\n<a href=\"htt",
                "uid": "68314"
            },
            "2.1.3": {
                "name": "wordpress\/embedly",
                "version": "2.1.3",
                "version_normalized": "2.1.3.0",
                "dist": {
                    "type": "zip",
                    "url": "http:\/\/downloads.wordpress.org\/plugin\/embedly.2.1.3.zip",
                    "reference": null,
                    "shasum": null
                },
                "require": {
                    "wordpress\/installer": "0.1.*"
                },
                "type": "wordpress-plugin",
                "description": "<p>The <a href=\"http:\/\/embed.ly\">Embedly<\/a> plugin allows bloggers to embed videos, images, PDF, and article previews from\n\"any\" source with just the URL. It uses the <a href=\"http:\/\/embed.ly\/docs\">Embedly API<\/a> to\nget the embed code and display it in a post.<\/p>\n\n<p>Write your post as normal and click the Embedly Icon in your Rich Editor\nto add \"any\" URL to your post.<\/p>\n\n<p>OR<\/p>\n\n<p>Embed 200+ sources by putting the URL to the content you want to embed on\na single line like so:<\/p>\n\n<pre><code>This Embedly lets me embed everything great on the web!\n\n<a href=\"http:\/\/twitpic.com\/1owy89\" rel=\"nofollow\">http:\/\/twitpic.com\/1owy89<\/a>\n\n<a href=\"http:\/\/i.imgur.com\/ywzpg.jpg\" rel=\"nofollow\">http:\/\/i.imgur.com\/ywzpg.jpg<\/a>\n\n<a href=\"http:\/\/www.amazon.com\/gp\/product\/B002BRZ9G0\/ref=s9_pop_gw_ir01\" rel=\"nofollow\">http:\/\/www.amazon.com\/gp\/product\/B002BRZ9G0\/ref=s9_pop_gw_ir01<\/a>\n\n<a href=\"http:\/\/twitter.com\/jack\/status\/20\" rel=\"nofollow\">http:\/\/twitter.com\/jack\/status\/20<\/a>\n\n<a href=\"htt",
                "uid": "68313"
            },
            "2.1.4": {
                "name": "wordpress\/embedly",
                "version": "2.1.4",
                "version_normalized": "2.1.4.0",
                "dist": {
                    "type": "zip",
                    "url": "http:\/\/downloads.wordpress.org\/plugin\/embedly.2.1.4.zip",
                    "reference": null,
                    "shasum": null
                },
                "require": {
                    "wordpress\/installer": "0.1.*"
                },
                "type": "wordpress-plugin",
                "description": "<p>The <a href=\"http:\/\/embed.ly\">Embedly<\/a> plugin allows bloggers to embed videos, images, PDF, and article previews from\n\"any\" source with just the URL. It uses the <a href=\"http:\/\/embed.ly\/docs\">Embedly API<\/a> to\nget the embed code and display it in a post.<\/p>\n\n<p>Write your post as normal and click the Embedly Icon in your Rich Editor\nto add \"any\" URL to your post.<\/p>\n\n<p>OR<\/p>\n\n<p>Embed 200+ sources by putting the URL to the content you want to embed on\na single line like so:<\/p>\n\n<pre><code>This Embedly lets me embed everything great on the web!\n\n<a href=\"http:\/\/twitpic.com\/1owy89\" rel=\"nofollow\">http:\/\/twitpic.com\/1owy89<\/a>\n\n<a href=\"http:\/\/i.imgur.com\/ywzpg.jpg\" rel=\"nofollow\">http:\/\/i.imgur.com\/ywzpg.jpg<\/a>\n\n<a href=\"http:\/\/www.amazon.com\/gp\/product\/B002BRZ9G0\/ref=s9_pop_gw_ir01\" rel=\"nofollow\">http:\/\/www.amazon.com\/gp\/product\/B002BRZ9G0\/ref=s9_pop_gw_ir01<\/a>\n\n<a href=\"http:\/\/twitter.com\/jack\/status\/20\" rel=\"nofollow\">http:\/\/twitter.com\/jack\/status\/20<\/a>\n\n<a href=\"htt",
                "uid": "118730"
            },
            "2.1.5": {
                "name": "wordpress\/embedly",
                "version": "2.1.5",
                "version_normalized": "2.1.5.0",
                "dist": {
                    "type": "zip",
                    "url": "http:\/\/downloads.wordpress.org\/plugin\/embedly.2.1.5.zip",
                    "reference": null,
                    "shasum": null
                },
                "require": {
                    "wordpress\/installer": "0.1.*"
                },
                "type": "wordpress-plugin",
                "description": "<p>The <a href=\"http:\/\/embed.ly\">Embedly<\/a> plugin allows bloggers to embed videos, images, PDF, and article previews from\n\"any\" source with just the URL. It uses the <a href=\"http:\/\/embed.ly\/docs\">Embedly API<\/a> to\nget the embed code and display it in a post.<\/p>\n\n<p>Write your post as normal and click the Embedly Icon in your Rich Editor\nto add \"any\" URL to your post.<\/p>\n\n<p>OR<\/p>\n\n<p>Embed 200+ sources by putting the URL to the content you want to embed on\na single line like so:<\/p>\n\n<pre><code>This Embedly lets me embed everything great on the web!\n\n<a href=\"http:\/\/twitpic.com\/1owy89\" rel=\"nofollow\">http:\/\/twitpic.com\/1owy89<\/a>\n\n<a href=\"http:\/\/i.imgur.com\/ywzpg.jpg\" rel=\"nofollow\">http:\/\/i.imgur.com\/ywzpg.jpg<\/a>\n\n<a href=\"http:\/\/www.amazon.com\/gp\/product\/B002BRZ9G0\/ref=s9_pop_gw_ir01\" rel=\"nofollow\">http:\/\/www.amazon.com\/gp\/product\/B002BRZ9G0\/ref=s9_pop_gw_ir01<\/a>\n\n<a href=\"http:\/\/twitter.com\/jack\/status\/20\" rel=\"nofollow\">http:\/\/twitter.com\/jack\/status\/20<\/a>\n\n<a href=\"htt",
                "uid": "118729"
            }
        }
    }
}