{
    "packages": {
        "wordpress\/jetpack-post-statistic-link-plugin": {
            "1.0.0": {
                "name": "wordpress\/jetpack-post-statistic-link-plugin",
                "version": "1.0.0",
                "version_normalized": "1.0.0.0",
                "dist": {
                    "type": "zip",
                    "url": "http:\/\/downloads.wordpress.org\/plugin\/jetpack-post-statistic-link-plugin.1.0.0.zip",
                    "reference": null,
                    "shasum": null
                },
                "require": {
                    "wordpress\/installer": "0.1.*"
                },
                "type": "wordpress-plugin",
                "description": "<p>Adds a custom column to the Posts Admin page that provides a link to the JetPack Statistics for each post on your blog.<\/p>\n\n<p>Pre-Requisite:<\/p>\n\n<ul>\n<li>You must have Jetpack installed and active on your wordpress blog.<\/li>\n<li>First released against Jetpack version 1.2.4. <\/li>\n<li>Tested to work with JetPack 2.1.1<\/li>\n<\/ul>",
                "uid": "31455"
            },
            "1.1.0": {
                "name": "wordpress\/jetpack-post-statistic-link-plugin",
                "version": "1.1.0",
                "version_normalized": "1.1.0.0",
                "dist": {
                    "type": "zip",
                    "url": "http:\/\/downloads.wordpress.org\/plugin\/jetpack-post-statistic-link-plugin.1.1.0.zip",
                    "reference": null,
                    "shasum": null
                },
                "require": {
                    "wordpress\/installer": "0.1.*"
                },
                "type": "wordpress-plugin",
                "description": "<p>Adds a custom column to the Posts Admin page that provides a link to the JetPack Statistics for each post on your blog.<\/p>\n\n<p>Pre-Requisite:<\/p>\n\n<ul>\n<li>You must have Jetpack installed and active on your wordpress blog.<\/li>\n<li>First released against Jetpack version 1.2.4. <\/li>\n<li>Tested to work with JetPack 2.1.1<\/li>\n<\/ul>",
                "uid": "31454"
            },
            "1.2.0": {
                "name": "wordpress\/jetpack-post-statistic-link-plugin",
                "version": "1.2.0",
                "version_normalized": "1.2.0.0",
                "dist": {
                    "type": "zip",
                    "url": "http:\/\/downloads.wordpress.org\/plugin\/jetpack-post-statistic-link-plugin.1.2.0.zip",
                    "reference": null,
                    "shasum": null
                },
                "require": {
                    "wordpress\/installer": "0.1.*"
                },
                "type": "wordpress-plugin",
                "description": "<p>Adds a custom column to the Posts Admin page that provides a link to the JetPack Statistics for each post on your blog.<\/p>\n\n<p>Pre-Requisite:<\/p>\n\n<ul>\n<li>You must have Jetpack installed and active on your wordpress blog.<\/li>\n<li>First released against Jetpack version 1.2.4. <\/li>\n<li>Tested to work with JetPack 2.1.1<\/li>\n<\/ul>",
                "uid": "31453"
            }
        }
    }
}