{
    "packages": {
        "wordpress\/portfolio-media": {
            "1.0": {
                "name": "wordpress\/portfolio-media",
                "version": "1.0",
                "version_normalized": "1.0.0.0",
                "dist": {
                    "type": "zip",
                    "url": "http:\/\/downloads.wordpress.org\/plugin\/portfolio-media.1.0.zip",
                    "reference": null,
                    "shasum": null
                },
                "require": {
                    "wordpress\/installer": "0.1.*"
                },
                "type": "wordpress-plugin",
                "description": "<p>The Portfolio Media plugin allows you to implement a portfolio based gallery. This uses a portfolio media post type to manage portfolio based posts and allows users to attach media objects to them in a similar way 'featured image' works. This works for image and video file formats only.<\/p>",
                "uid": "9385"
            },
            "1.1": {
                "name": "wordpress\/portfolio-media",
                "version": "1.1",
                "version_normalized": "1.1.0.0",
                "dist": {
                    "type": "zip",
                    "url": "http:\/\/downloads.wordpress.org\/plugin\/portfolio-media.1.1.zip",
                    "reference": null,
                    "shasum": null
                },
                "require": {
                    "wordpress\/installer": "0.1.*"
                },
                "type": "wordpress-plugin",
                "description": "<p>The Portfolio Media plugin allows you to implement a portfolio based gallery. This uses a portfolio media post type to manage portfolio based posts and allows users to attach media objects to them in a similar way 'featured image' works. This works for image and video file formats only.<\/p>",
                "uid": "9384"
            }
        }
    }
}